SGCC/__init__.py
SGCC/__main__.py
SGCC/savgol.py
SGCC/savgol_poly.py
savgol_calculator-1.0.5.dist-info/METADATA
savgol_calculator-1.0.5.dist-info/WHEEL
savgol_calculator-1.0.5.dist-info/top_level.txt
savgol_calculator-1.0.5.dist-info/RECORD
