Metadata-Version: 2.1
Name: savgol-calculator
Version: 1.0.5
Summary: Python implementation of a coefficients calculator for the Savitsky-Golay filter with any parameters.
Home-page: https://github.com/dvidbruhm/savgol-calculator
Author: dvidbruhm
Author-email: david.abraham.1337@gmail.com
License: MIT
Platform: UNKNOWN
Classifier: License :: OSI Approved :: MIT License
Classifier: Programming Language :: Python
Classifier: Programming Language :: Python :: 3
Classifier: Programming Language :: Python :: 3.6
Classifier: Programming Language :: Python :: Implementation :: CPython
Classifier: Programming Language :: Python :: Implementation :: PyPy
Requires-Python: >=3.6.0
